circleclient/__init__.py
circleclient/circleclient.py
circleclient-0.1.6.dist-info/metadata.json
circleclient-0.1.6.dist-info/top_level.txt
circleclient-0.1.6.dist-info/WHEEL
circleclient-0.1.6.dist-info/RECORD
circleclient-0.1.6.dist-info/DESCRIPTION.rst
circleclient-0.1.6.dist-info/METADATA
