Metadata-Version: 2.0
Name: circleclient
Version: 0.1.6
Summary: Python client for CircleCI API
Home-page: http://github.com/qba73/circleclient/
Author: Jakub Jarosz
Author-email: qba73@postpro.net
License: MIT
Keywords: ci,testing,qa,circleclient
Platform: UNKNOWN
Classifier: Development Status :: 3 - Alpha
Classifier: Environment :: Console
Classifier: Intended Audience :: Developers
Classifier: License :: OSI Approved :: MIT License
Classifier: Natural Language :: English
Classifier: Programming Language :: Python :: 2
Classifier: Programming Language :: Python :: 2.7
Classifier: Programming Language :: Python :: 3
Classifier: Programming Language :: Python :: 3.3
Classifier: Programming Language :: Python :: 3.4
Classifier: Topic :: Software Development :: Testing
Classifier: Topic :: Software Development :: Quality Assurance
Requires-Dist: requests
